[
  {
    "id": 1,
    "firstName": "Torie",
    "lastName": "Rustman",
    "email": "trustman0@amazon.co.uk",
    "dateOfBirth": "1979-11-16T23:04:32Z",
    "age": 45,
    "country": "Argentina",
    "phone": "6844103517"
  },
  {
    "id": 2,
    "firstName": "Kordula",
    "lastName": "Gecks",
    "email": "kgecks1@deviantart.com",
    "dateOfBirth": "1997-08-06T21:07:34Z",
    "age": 30,
    "country": "Greece",
    "phone": "8429683893"
  },
  {
    "id": 3,
    "firstName": "Vikki",
    "lastName": "Simoens",
    "email": "vsimoens2@ted.com",
    "dateOfBirth": "2016-04-28T16:59:19Z",
    "age": 48,
    "country": "Czech Republic",
    "phone": "8672773997"
  },
  {
    "id": 4,
    "firstName": "Burnaby",
    "lastName": "Cowern",
    "email": "bcowern3@forbes.com",
    "dateOfBirth": "2017-10-25T08:05:50Z",
    "age": 54,
    "country": "Equatorial Guinea",
    "phone": "4257971694"
  },
  {
    "id": 5,
    "firstName": "Teddie",
    "lastName": "Traice",
    "email": "ttraice4@zdnet.com",
    "dateOfBirth": "2015-04-20T11:45:34Z",
    "age": 57,
    "country": "Russia",
    "phone": "3932158370"
  },
  {
    "id": 6,
    "firstName": "Sapphira",
    "lastName": "Hutchinges",
    "email": "shutchinges5@cam.ac.uk",
    "dateOfBirth": "1995-06-15T22:08:17Z",
    "age": 53,
    "country": "Ethiopia",
    "phone": "5094928131"
  },
  {
    "id": 7,
    "firstName": "Shayna",
    "lastName": "Dimitresco",
    "email": "sdimitresco6@uiuc.edu",
    "dateOfBirth": "1997-10-28T11:25:07Z",
    "age": 21,
    "country": "Indonesia",
    "phone": "1216713219"
  },
  {
    "id": 8,
    "firstName": "Caron",
    "lastName": "Tomkinson",
    "email": "ctomkinson7@nature.com",
    "dateOfBirth": "1989-03-14T19:48:26Z",
    "age": 47,
    "country": "Ukraine",
    "phone": "6895680771"
  },
  {
    "id": 9,
    "firstName": "Hulda",
    "lastName": "Ceresa",
    "email": "hceresa8@omniture.com",
    "dateOfBirth": "2016-04-26T18:07:18Z",
    "age": 24,
    "country": "United Arab Emirates",
    "phone": "2117090201"
  },
  {
    "id": 10,
    "firstName": "Neile",
    "lastName": "Clements",
    "email": "nclements9@irs.gov",
    "dateOfBirth": "2001-05-22T23:12:25Z",
    "age": 39,
    "country": "Ukraine",
    "phone": "5863355971"
  },
  {
    "id": 11,
    "firstName": "Denver",
    "lastName": "Pagnin",
    "email": "dpagnina@opensource.org",
    "dateOfBirth": "1973-11-25T18:08:41Z",
    "age": 33,
    "country": "Indonesia",
    "phone": "8637568504"
  },
  {
    "id": 12,
    "firstName": "Louella",
    "lastName": "Carlill",
    "email": "lcarlillb@webs.com",
    "dateOfBirth": "2008-12-09T09:54:05Z",
    "age": 28,
    "country": "Philippines",
    "phone": "8427969519"
  },
  {
    "id": 13,
    "firstName": "Margarita",
    "lastName": "Lewknor",
    "email": "mlewknorc@spiegel.de",
    "dateOfBirth": "2002-05-29T03:19:27Z",
    "age": 49,
    "country": "Philippines",
    "phone": "6564638302"
  },
  {
    "id": 14,
    "firstName": "Elise",
    "lastName": "Petruska",
    "email": "epetruskad@51.la",
    "dateOfBirth": "1980-04-07T12:02:49Z",
    "age": 19,
    "country": "Russia",
    "phone": "4848143050"
  },
  {
    "id": 15,
    "firstName": "Consuela",
    "lastName": "Birtwistle",
    "email": "cbirtwistlee@pbs.org",
    "dateOfBirth": "2010-11-09T15:16:20Z",
    "age": 24,
    "country": "Philippines",
    "phone": "8823245128"
  },
  {
    "id": 16,
    "firstName": "Moise",
    "lastName": "Hugett",
    "email": "mhugettf@sfgate.com",
    "dateOfBirth": "1992-09-21T20:05:24Z",
    "age": 58,
    "country": "Palestinian Territory",
    "phone": "4884280161"
  },
  {
    "id": 17,
    "firstName": "Emiline",
    "lastName": "Foucard",
    "email": "efoucardg@weibo.com",
    "dateOfBirth": "1986-12-27T18:40:36Z",
    "age": 30,
    "country": "Indonesia",
    "phone": "8772777497"
  },
  {
    "id": 18,
    "firstName": "Rosaleen",
    "lastName": "Ionesco",
    "email": "rionescoh@typepad.com",
    "dateOfBirth": "2004-05-18T18:25:24Z",
    "age": 28,
    "country": "Russia",
    "phone": "3528274607"
  },
  {
    "id": 19,
    "firstName": "William",
    "lastName": "Kivlin",
    "email": "wkivlini@usgs.gov",
    "dateOfBirth": "2000-05-23T10:30:27Z",
    "age": 53,
    "country": "France",
    "phone": "8684362846"
  },
  {
    "id": 20,
    "firstName": "Tallie",
    "lastName": "Keenleyside",
    "email": "tkeenleysidej@google.com.br",
    "dateOfBirth": "1991-10-12T07:19:00Z",
    "age": 33,
    "country": "Cuba",
    "phone": "6295519396"
  },
  {
    "id": 21,
    "firstName": "Kinny",
    "lastName": "Brazelton",
    "email": "kbrazeltonk@whitehouse.gov",
    "dateOfBirth": "2017-10-22T08:46:50Z",
    "age": 49,
    "country": "Peru",
    "phone": "7213448846"
  },
  {
    "id": 22,
    "firstName": "Tybi",
    "lastName": "Papworth",
    "email": "tpapworthl@auda.org.au",
    "dateOfBirth": "1979-10-14T19:06:50Z",
    "age": 52,
    "country": "Indonesia",
    "phone": "6514139986"
  },
  {
    "id": 23,
    "firstName": "Caria",
    "lastName": "Crudge",
    "email": "ccrudgem@devhub.com",
    "dateOfBirth": "2019-09-11T16:35:47Z",
    "age": 47,
    "country": "Poland",
    "phone": "1313207773"
  },
  {
    "id": 24,
    "firstName": "Justin",
    "lastName": "Luebbert",
    "email": "jluebbertn@ucsd.edu",
    "dateOfBirth": "1995-07-08T11:07:24Z",
    "age": 55,
    "country": "Sweden",
    "phone": "1892172806"
  },
  {
    "id": 25,
    "firstName": "Dusty",
    "lastName": "Allan",
    "email": "dallano@issuu.com",
    "dateOfBirth": "1974-12-11T13:53:55Z",
    "age": 49,
    "country": "Russia",
    "phone": "9536828334"
  },
  {
    "id": 26,
    "firstName": "Andrej",
    "lastName": "Paynes",
    "email": "apaynesp@fotki.com",
    "dateOfBirth": "2009-01-06T21:56:45Z",
    "age": 35,
    "country": "Colombia",
    "phone": "6312207567"
  },
  {
    "id": 27,
    "firstName": "Bartel",
    "lastName": "Ennor",
    "email": "bennorq@illinois.edu",
    "dateOfBirth": "1988-03-26T13:04:21Z",
    "age": 21,
    "country": "Indonesia",
    "phone": "9971111062"
  },
  {
    "id": 28,
    "firstName": "Cindy",
    "lastName": "Tabram",
    "email": "ctabramr@state.tx.us",
    "dateOfBirth": "2010-03-09T09:14:45Z",
    "age": 45,
    "country": "United States",
    "phone": "6269225638"
  },
  {
    "id": 29,
    "firstName": "Lorinda",
    "lastName": "McIleen",
    "email": "lmcileens@hugedomains.com",
    "dateOfBirth": "1992-10-27T12:49:57Z",
    "age": 56,
    "country": "Ivory Coast",
    "phone": "2627894839"
  },
  {
    "id": 30,
    "firstName": "Roseline",
    "lastName": "Kryszkiecicz",
    "email": "rkryszkieciczt@simplemachines.org",
    "dateOfBirth": "1981-01-22T21:58:08Z",
    "age": 42,
    "country": "China",
    "phone": "8944652389"
  },
  {
    "id": 31,
    "firstName": "Gustaf",
    "lastName": "Yonge",
    "email": "gyongeu@yahoo.com",
    "dateOfBirth": "1989-05-31T09:29:39Z",
    "age": 21,
    "country": "Indonesia",
    "phone": "5358175227"
  },
  {
    "id": 32,
    "firstName": "Rozanna",
    "lastName": "Duesbury",
    "email": "rduesburyv@buzzfeed.com",
    "dateOfBirth": "1973-01-01T23:04:04Z",
    "age": 54,
    "country": "Czech Republic",
    "phone": "9048047315"
  },
  {
    "id": 33,
    "firstName": "Faber",
    "lastName": "Zelland",
    "email": "fzellandw@mit.edu",
    "dateOfBirth": "2012-08-25T07:33:41Z",
    "age": 48,
    "country": "United States",
    "phone": "5618492219"
  },
  {
    "id": 34,
    "firstName": "Bryanty",
    "lastName": "Swainsbury",
    "email": "bswainsburyx@reference.com",
    "dateOfBirth": "2002-10-22T18:09:15Z",
    "age": 56,
    "country": "Canada",
    "phone": "5765823562"
  },
  {
    "id": 35,
    "firstName": "Phylys",
    "lastName": "Durek",
    "email": "pdureky@eventbrite.com",
    "dateOfBirth": "1989-04-19T14:24:55Z",
    "age": 30,
    "country": "Philippines",
    "phone": "3264797290"
  },
  {
    "id": 36,
    "firstName": "Quint",
    "lastName": "Beaston",
    "email": "qbeastonz@ehow.com",
    "dateOfBirth": "1971-09-10T19:34:04Z",
    "age": 29,
    "country": "Finland",
    "phone": "9657407673"
  },
  {
    "id": 37,
    "firstName": "Natalina",
    "lastName": "Gossop",
    "email": "ngossop10@sbwire.com",
    "dateOfBirth": "2019-08-23T22:59:26Z",
    "age": 48,
    "country": "Indonesia",
    "phone": "9922842223"
  },
  {
    "id": 38,
    "firstName": "Rich",
    "lastName": "Halversen",
    "email": "rhalversen11@state.gov",
    "dateOfBirth": "1977-03-24T05:36:22Z",
    "age": 36,
    "country": "Turkmenistan",
    "phone": "2185875902"
  },
  {
    "id": 39,
    "firstName": "Denice",
    "lastName": "Pieroni",
    "email": "dpieroni12@bravesites.com",
    "dateOfBirth": "1974-01-10T05:54:58Z",
    "age": 25,
    "country": "Brazil",
    "phone": "2944772525"
  },
  {
    "id": 40,
    "firstName": "Annie",
    "lastName": "Rothermel",
    "email": "arothermel13@ucoz.com",
    "dateOfBirth": "2002-09-24T16:23:46Z",
    "age": 55,
    "country": "Sweden",
    "phone": "5825313358"
  },
  {
    "id": 41,
    "firstName": "Karina",
    "lastName": "Drury",
    "email": "kdrury14@google.ru",
    "dateOfBirth": "1990-01-12T09:33:25Z",
    "age": 25,
    "country": "Iran",
    "phone": "6085536064"
  },
  {
    "id": 42,
    "firstName": "Aube",
    "lastName": "Chretien",
    "email": "achretien15@cbslocal.com",
    "dateOfBirth": "1999-03-29T23:33:39Z",
    "age": 36,
    "country": "France",
    "phone": "9176021911"
  },
  {
    "id": 43,
    "firstName": "Cyndie",
    "lastName": "Pyecroft",
    "email": "cpyecroft16@blogger.com",
    "dateOfBirth": "1992-01-08T05:48:26Z",
    "age": 36,
    "country": "Indonesia",
    "phone": "5536086300"
  },
  {
    "id": 44,
    "firstName": "Perry",
    "lastName": "Ovett",
    "email": "povett17@icio.us",
    "dateOfBirth": "2004-09-02T02:53:46Z",
    "age": 32,
    "country": "Philippines",
    "phone": "5501653348"
  },
  {
    "id": 45,
    "firstName": "Nestor",
    "lastName": "Eddington",
    "email": "neddington18@nature.com",
    "dateOfBirth": "1973-08-05T15:58:05Z",
    "age": 42,
    "country": "Paraguay",
    "phone": "8104333778"
  },
  {
    "id": 46,
    "firstName": "Beckie",
    "lastName": "Venneur",
    "email": "bvenneur19@discuz.net",
    "dateOfBirth": "1994-08-10T05:43:50Z",
    "age": 52,
    "country": "Indonesia",
    "phone": "5405031314"
  },
  {
    "id": 47,
    "firstName": "Maje",
    "lastName": "Pert",
    "email": "mpert1a@timesonline.co.uk",
    "dateOfBirth": "2002-12-12T18:38:35Z",
    "age": 22,
    "country": "Guatemala",
    "phone": "4768506969"
  },
  {
    "id": 48,
    "firstName": "Matthias",
    "lastName": "Purver",
    "email": "mpurver1b@ocn.ne.jp",
    "dateOfBirth": "1973-03-07T07:12:50Z",
    "age": 36,
    "country": "France",
    "phone": "9765669240"
  },
  {
    "id": 49,
    "firstName": "Wileen",
    "lastName": "Physick",
    "email": "wphysick1c@imageshack.us",
    "dateOfBirth": "1971-02-14T05:03:05Z",
    "age": 36,
    "country": "Denmark",
    "phone": "5051073396"
  },
  {
    "id": 50,
    "firstName": "Wilhelm",
    "lastName": "Giacobilio",
    "email": "wgiacobilio1d@shinystat.com",
    "dateOfBirth": "1991-02-22T16:46:58Z",
    "age": 35,
    "country": "Indonesia",
    "phone": "7851525795"
  },
  {
    "id": 51,
    "firstName": "Thorpe",
    "lastName": "Pavie",
    "email": "tpavie1e@wordpress.org",
    "dateOfBirth": "1991-12-03T06:28:39Z",
    "age": 47,
    "country": "Philippines",
    "phone": "8321134681"
  },
  {
    "id": 52,
    "firstName": "Stavros",
    "lastName": "Marzelle",
    "email": "smarzelle1f@berkeley.edu",
    "dateOfBirth": "2003-02-12T14:06:26Z",
    "age": 19,
    "country": "Poland",
    "phone": "2589170552"
  },
  {
    "id": 53,
    "firstName": "Melina",
    "lastName": "Stealy",
    "email": "mstealy1g@theatlantic.com",
    "dateOfBirth": "1971-02-14T18:32:42Z",
    "age": 50,
    "country": "China",
    "phone": "2953061731"
  },
  {
    "id": 54,
    "firstName": "Lee",
    "lastName": "Cosbey",
    "email": "lcosbey1h@parallels.com",
    "dateOfBirth": "2010-02-02T09:12:30Z",
    "age": 56,
    "country": "Indonesia",
    "phone": "6186571451"
  },
  {
    "id": 55,
    "firstName": "Virge",
    "lastName": "Kinvig",
    "email": "vkinvig1i@freewebs.com",
    "dateOfBirth": "2019-03-07T13:22:09Z",
    "age": 47,
    "country": "Netherlands",
    "phone": "4264980180"
  },
  {
    "id": 56,
    "firstName": "April",
    "lastName": "Town",
    "email": "atown1j@japanpost.jp",
    "dateOfBirth": "2013-05-13T04:10:42Z",
    "age": 51,
    "country": "Uganda",
    "phone": "7813787304"
  },
  {
    "id": 57,
    "firstName": "Ferd",
    "lastName": "Clausen",
    "email": "fclausen1k@mac.com",
    "dateOfBirth": "2014-10-13T13:41:19Z",
    "age": 47,
    "country": "Indonesia",
    "phone": "1637727947"
  },
  {
    "id": 58,
    "firstName": "Trudey",
    "lastName": "Gagg",
    "email": "tgagg1l@webmd.com",
    "dateOfBirth": "2016-06-04T22:10:39Z",
    "age": 52,
    "country": "China",
    "phone": "6566643109"
  },
  {
    "id": 59,
    "firstName": "Nissa",
    "lastName": "McLagain",
    "email": "nmclagain1m@nhs.uk",
    "dateOfBirth": "2015-04-17T18:07:43Z",
    "age": 48,
    "country": "Indonesia",
    "phone": "2747697147"
  },
  {
    "id": 60,
    "firstName": "Cherianne",
    "lastName": "Ivakhin",
    "email": "civakhin1n@japanpost.jp",
    "dateOfBirth": "1986-03-27T03:15:36Z",
    "age": 37,
    "country": "Madagascar",
    "phone": "4471164344"
  },
  {
    "id": 61,
    "firstName": "Myrna",
    "lastName": "Thomlinson",
    "email": "mthomlinson1o@tinypic.com",
    "dateOfBirth": "1991-05-29T23:09:49Z",
    "age": 36,
    "country": "Malaysia",
    "phone": "4313867084"
  },
  {
    "id": 62,
    "firstName": "Hunter",
    "lastName": "Juster",
    "email": "hjuster1p@devhub.com",
    "dateOfBirth": "2005-04-16T08:03:12Z",
    "age": 46,
    "country": "China",
    "phone": "8196747617"
  },
  {
    "id": 63,
    "firstName": "Raff",
    "lastName": "Halsworth",
    "email": "rhalsworth1q@youku.com",
    "dateOfBirth": "2015-09-27T07:22:34Z",
    "age": 40,
    "country": "Indonesia",
    "phone": "7924421227"
  },
  {
    "id": 64,
    "firstName": "Kat",
    "lastName": "Preddle",
    "email": "kpreddle1r@twitpic.com",
    "dateOfBirth": "1987-06-28T03:44:38Z",
    "age": 45,
    "country": "Peru",
    "phone": "2512277614"
  },
  {
    "id": 65,
    "firstName": "Samara",
    "lastName": "Regglar",
    "email": "sregglar1s@elegantthemes.com",
    "dateOfBirth": "2005-05-05T03:10:00Z",
    "age": 39,
    "country": "United States",
    "phone": "2535773207"
  },
  {
    "id": 66,
    "firstName": "Sarina",
    "lastName": "Fairest",
    "email": "sfairest1t@google.es",
    "dateOfBirth": "2005-09-01T20:35:38Z",
    "age": 23,
    "country": "Uzbekistan",
    "phone": "6713074482"
  },
  {
    "id": 67,
    "firstName": "Josy",
    "lastName": "Hitzschke",
    "email": "jhitzschke1u@washingtonpost.com",
    "dateOfBirth": "2014-01-04T05:57:30Z",
    "age": 55,
    "country": "China",
    "phone": "6128279765"
  },
  {
    "id": 68,
    "firstName": "Michael",
    "lastName": "Viscovi",
    "email": "mviscovi1v@businessinsider.com",
    "dateOfBirth": "2019-03-27T10:04:10Z",
    "age": 22,
    "country": "Argentina",
    "phone": "6083493037"
  },
  {
    "id": 69,
    "firstName": "Arlena",
    "lastName": "Kinmond",
    "email": "akinmond1w@yolasite.com",
    "dateOfBirth": "1994-11-27T18:38:04Z",
    "age": 33,
    "country": "Indonesia",
    "phone": "7583463942"
  },
  {
    "id": 70,
    "firstName": "Abigail",
    "lastName": "Okey",
    "email": "aokey1x@de.vu",
    "dateOfBirth": "1993-04-26T10:58:24Z",
    "age": 30,
    "country": "Cuba",
    "phone": "2438993383"
  },
  {
    "id": 71,
    "firstName": "Erv",
    "lastName": "Paoletto",
    "email": "epaoletto1y@seesaa.net",
    "dateOfBirth": "1980-03-10T04:38:40Z",
    "age": 32,
    "country": "Cameroon",
    "phone": "7609648254"
  },
  {
    "id": 72,
    "firstName": "Nicole",
    "lastName": "Blowers",
    "email": "nblowers1z@wired.com",
    "dateOfBirth": "1978-03-19T04:31:59Z",
    "age": 49,
    "country": "Russia",
    "phone": "6784962674"
  },
  {
    "id": 73,
    "firstName": "Burt",
    "lastName": "Dytham",
    "email": "bdytham20@huffingtonpost.com",
    "dateOfBirth": "2004-12-24T21:46:30Z",
    "age": 58,
    "country": "Serbia",
    "phone": "2793771822"
  },
  {
    "id": 74,
    "firstName": "Allissa",
    "lastName": "Lope",
    "email": "alope21@samsung.com",
    "dateOfBirth": "2005-02-12T08:53:47Z",
    "age": 19,
    "country": "China",
    "phone": "8221598625"
  },
  {
    "id": 75,
    "firstName": "Sayre",
    "lastName": "Archbold",
    "email": "sarchbold22@icio.us",
    "dateOfBirth": "1987-01-25T22:32:22Z",
    "age": 49,
    "country": "Iran",
    "phone": "6988431419"
  },
  {
    "id": 76,
    "firstName": "Caty",
    "lastName": "Swatradge",
    "email": "cswatradge23@businessinsider.com",
    "dateOfBirth": "2016-07-19T21:45:00Z",
    "age": 52,
    "country": "Morocco",
    "phone": "6621582991"
  },
  {
    "id": 77,
    "firstName": "Daffie",
    "lastName": "Windmill",
    "email": "dwindmill24@washingtonpost.com",
    "dateOfBirth": "2005-01-01T09:55:14Z",
    "age": 41,
    "country": "Sweden",
    "phone": "2433090490"
  },
  {
    "id": 78,
    "firstName": "Maddalena",
    "lastName": "Baird",
    "email": "mbaird25@globo.com",
    "dateOfBirth": "1980-08-02T12:48:43Z",
    "age": 43,
    "country": "Poland",
    "phone": "9023312384"
  },
  {
    "id": 79,
    "firstName": "Killian",
    "lastName": "L'Archer",
    "email": "klarcher26@geocities.jp",
    "dateOfBirth": "1985-05-30T04:59:32Z",
    "age": 27,
    "country": "Indonesia",
    "phone": "5091131435"
  },
  {
    "id": 80,
    "firstName": "Editha",
    "lastName": "Millsap",
    "email": "emillsap27@indiegogo.com",
    "dateOfBirth": "1994-08-31T17:13:57Z",
    "age": 18,
    "country": "Indonesia",
    "phone": "1176370530"
  },
  {
    "id": 81,
    "firstName": "Ola",
    "lastName": "Isenor",
    "email": "oisenor28@irs.gov",
    "dateOfBirth": "1975-03-15T05:56:35Z",
    "age": 50,
    "country": "Thailand",
    "phone": "2323471722"
  },
  {
    "id": 82,
    "firstName": "Tripp",
    "lastName": "Barrat",
    "email": "tbarrat29@google.co.uk",
    "dateOfBirth": "2016-12-03T06:14:18Z",
    "age": 41,
    "country": "Portugal",
    "phone": "3392918464"
  },
  {
    "id": 83,
    "firstName": "Ernesto",
    "lastName": "Petrello",
    "email": "epetrello2a@themeforest.net",
    "dateOfBirth": "2015-02-07T14:53:47Z",
    "age": 48,
    "country": "Japan",
    "phone": "1819474989"
  },
  {
    "id": 84,
    "firstName": "Salome",
    "lastName": "Ratlee",
    "email": "sratlee2b@cafepress.com",
    "dateOfBirth": "1983-09-16T11:51:30Z",
    "age": 42,
    "country": "China",
    "phone": "8979986442"
  },
  {
    "id": 85,
    "firstName": "Gilli",
    "lastName": "Doig",
    "email": "gdoig2c@apple.com",
    "dateOfBirth": "2007-10-07T02:32:11Z",
    "age": 26,
    "country": "Philippines",
    "phone": "8079971006"
  },
  {
    "id": 86,
    "firstName": "Orton",
    "lastName": "Poleye",
    "email": "opoleye2d@huffingtonpost.com",
    "dateOfBirth": "2011-06-21T11:26:28Z",
    "age": 29,
    "country": "Russia",
    "phone": "9048118038"
  },
  {
    "id": 87,
    "firstName": "Zed",
    "lastName": "Ryde",
    "email": "zryde2e@sitemeter.com",
    "dateOfBirth": "1988-07-09T07:33:49Z",
    "age": 21,
    "country": "Morocco",
    "phone": "2033460112"
  },
  {
    "id": 88,
    "firstName": "Travers",
    "lastName": "Petow",
    "email": "tpetow2f@biglobe.ne.jp",
    "dateOfBirth": "2002-07-03T07:10:57Z",
    "age": 38,
    "country": "Poland",
    "phone": "3317840072"
  },
  {
    "id": 89,
    "firstName": "Tobie",
    "lastName": "Schleicher",
    "email": "tschleicher2g@google.nl",
    "dateOfBirth": "1976-08-29T16:54:19Z",
    "age": 26,
    "country": "Sweden",
    "phone": "2391321735"
  },
  {
    "id": 90,
    "firstName": "Jdavie",
    "lastName": "Kopfen",
    "email": "jkopfen2h@shareasale.com",
    "dateOfBirth": "1998-05-25T16:59:40Z",
    "age": 33,
    "country": "Bolivia",
    "phone": "9294104700"
  },
  {
    "id": 91,
    "firstName": "Elisha",
    "lastName": "Garvagh",
    "email": "egarvagh2i@last.fm",
    "dateOfBirth": "1986-05-25T04:25:21Z",
    "age": 47,
    "country": "Oman",
    "phone": "7482834587"
  },
  {
    "id": 92,
    "firstName": "Pris",
    "lastName": "Weekland",
    "email": "pweekland2j@latimes.com",
    "dateOfBirth": "1980-05-05T13:09:32Z",
    "age": 20,
    "country": "Indonesia",
    "phone": "7704017299"
  },
  {
    "id": 93,
    "firstName": "Alvinia",
    "lastName": "Braisher",
    "email": "abraisher2k@symantec.com",
    "dateOfBirth": "1999-06-07T18:04:58Z",
    "age": 40,
    "country": "Mauritania",
    "phone": "6402964459"
  },
  {
    "id": 94,
    "firstName": "Leanora",
    "lastName": "Patman",
    "email": "lpatman2l@bloomberg.com",
    "dateOfBirth": "1990-10-24T12:14:37Z",
    "age": 31,
    "country": "Nepal",
    "phone": "2423477217"
  },
  {
    "id": 95,
    "firstName": "Georgetta",
    "lastName": "Derrington",
    "email": "gderrington2m@amazonaws.com",
    "dateOfBirth": "1996-02-29T21:31:36Z",
    "age": 46,
    "country": "Panama",
    "phone": "2859065673"
  },
  {
    "id": 96,
    "firstName": "Murray",
    "lastName": "Howsego",
    "email": "mhowsego2n@goo.ne.jp",
    "dateOfBirth": "2000-04-25T17:50:20Z",
    "age": 37,
    "country": "South Korea",
    "phone": "5167063734"
  },
  {
    "id": 97,
    "firstName": "Caroljean",
    "lastName": "Lodder",
    "email": "clodder2o@live.com",
    "dateOfBirth": "2004-03-13T11:18:22Z",
    "age": 33,
    "country": "China",
    "phone": "6779005870"
  },
  {
    "id": 98,
    "firstName": "Carmella",
    "lastName": "Hunton",
    "email": "chunton2p@cam.ac.uk",
    "dateOfBirth": "1981-12-03T08:18:55Z",
    "age": 58,
    "country": "China",
    "phone": "2649233158"
  },
  {
    "id": 99,
    "firstName": "Berty",
    "lastName": "Friday",
    "email": "bfriday2q@wsj.com",
    "dateOfBirth": "2010-05-20T19:26:21Z",
    "age": 56,
    "country": "Japan",
    "phone": "7701209743"
  },
  {
    "id": 100,
    "firstName": "Joey",
    "lastName": "Regnard",
    "email": "jregnard2r@ted.com",
    "dateOfBirth": "1987-01-26T04:51:32Z",
    "age": 26,
    "country": "Russia",
    "phone": "2852842249"
  },
  {
    "id": 101,
    "firstName": "Zebulen",
    "lastName": "Chatell",
    "email": "zchatell2s@fc2.com",
    "dateOfBirth": "1976-10-03T06:50:41Z",
    "age": 44,
    "country": "Indonesia",
    "phone": "1342635982"
  },
  {
    "id": 102,
    "firstName": "Marjory",
    "lastName": "Worsnup",
    "email": "mworsnup2t@who.int",
    "dateOfBirth": "1979-03-26T09:44:19Z",
    "age": 57,
    "country": "Indonesia",
    "phone": "6984893663"
  },
  {
    "id": 103,
    "firstName": "Aurilia",
    "lastName": "Cousins",
    "email": "acousins2u@1und1.de",
    "dateOfBirth": "2000-05-03T10:47:26Z",
    "age": 41,
    "country": "Poland",
    "phone": "4442277237"
  },
  {
    "id": 104,
    "firstName": "Helena",
    "lastName": "Burchell",
    "email": "hburchell2v@infoseek.co.jp",
    "dateOfBirth": "1975-09-12T00:39:54Z",
    "age": 27,
    "country": "Canada",
    "phone": "4086491594"
  },
  {
    "id": 105,
    "firstName": "Zulema",
    "lastName": "MacIlriach",
    "email": "zmacilriach2w@ed.gov",
    "dateOfBirth": "1989-01-11T19:06:36Z",
    "age": 32,
    "country": "Brazil",
    "phone": "5277901159"
  },
  {
    "id": 106,
    "firstName": "Sergeant",
    "lastName": "Henzer",
    "email": "shenzer2x@1und1.de",
    "dateOfBirth": "1971-09-27T22:12:42Z",
    "age": 46,
    "country": "Indonesia",
    "phone": "8807821364"
  },
  {
    "id": 107,
    "firstName": "Rubi",
    "lastName": "Blaza",
    "email": "rblaza2y@unc.edu",
    "dateOfBirth": "1976-01-23T15:34:55Z",
    "age": 55,
    "country": "Canada",
    "phone": "1786740968"
  },
  {
    "id": 108,
    "firstName": "Glynis",
    "lastName": "Dobey",
    "email": "gdobey2z@lycos.com",
    "dateOfBirth": "1981-09-25T02:38:15Z",
    "age": 29,
    "country": "South Africa",
    "phone": "6719639998"
  },
  {
    "id": 109,
    "firstName": "Diane-marie",
    "lastName": "Leighton",
    "email": "dleighton30@senate.gov",
    "dateOfBirth": "1998-04-12T23:16:49Z",
    "age": 58,
    "country": "Japan",
    "phone": "6446687005"
  },
  {
    "id": 110,
    "firstName": "Levy",
    "lastName": "Pellew",
    "email": "lpellew31@prlog.org",
    "dateOfBirth": "2018-11-09T23:18:27Z",
    "age": 53,
    "country": "Peru",
    "phone": "6137456636"
  },
  {
    "id": 111,
    "firstName": "Aila",
    "lastName": "Thorogood",
    "email": "athorogood32@exblog.jp",
    "dateOfBirth": "1975-01-19T04:09:11Z",
    "age": 27,
    "country": "Russia",
    "phone": "5594789451"
  },
  {
    "id": 112,
    "firstName": "Winifred",
    "lastName": "Albers",
    "email": "walbers33@furl.net",
    "dateOfBirth": "1974-07-22T18:54:03Z",
    "age": 37,
    "country": "Philippines",
    "phone": "2439838234"
  },
  {
    "id": 113,
    "firstName": "Ema",
    "lastName": "Ronchi",
    "email": "eronchi34@omniture.com",
    "dateOfBirth": "2009-03-04T03:07:33Z",
    "age": 18,
    "country": "Venezuela",
    "phone": "4367279139"
  },
  {
    "id": 114,
    "firstName": "Gabie",
    "lastName": "Sydney",
    "email": "gsydney35@google.com.hk",
    "dateOfBirth": "1992-06-23T06:20:20Z",
    "age": 30,
    "country": "Indonesia",
    "phone": "8939262347"
  },
  {
    "id": 115,
    "firstName": "Oralle",
    "lastName": "Lardez",
    "email": "olardez36@indiegogo.com",
    "dateOfBirth": "1990-11-13T19:53:54Z",
    "age": 39,
    "country": "Portugal",
    "phone": "4359299903"
  },
  {
    "id": 116,
    "firstName": "Sawyer",
    "lastName": "Stubs",
    "email": "sstubs37@macromedia.com",
    "dateOfBirth": "2005-07-26T12:35:28Z",
    "age": 49,
    "country": "Poland",
    "phone": "1861354169"
  },
  {
    "id": 117,
    "firstName": "Carr",
    "lastName": "Ventum",
    "email": "cventum38@google.com.br",
    "dateOfBirth": "1983-08-22T19:42:33Z",
    "age": 43,
    "country": "China",
    "phone": "4898905760"
  },
  {
    "id": 118,
    "firstName": "Dolly",
    "lastName": "Shovell",
    "email": "dshovell39@illinois.edu",
    "dateOfBirth": "2019-12-09T08:46:33Z",
    "age": 27,
    "country": "Nepal",
    "phone": "7357417362"
  },
  {
    "id": 119,
    "firstName": "Vick",
    "lastName": "Wealleans",
    "email": "vwealleans3a@artisteer.com",
    "dateOfBirth": "2016-05-27T22:49:51Z",
    "age": 43,
    "country": "Canada",
    "phone": "7438739565"
  },
  {
    "id": 120,
    "firstName": "Nilson",
    "lastName": "Artz",
    "email": "nartz3b@answers.com",
    "dateOfBirth": "1996-12-09T00:05:09Z",
    "age": 46,
    "country": "Philippines",
    "phone": "4274227531"
  },
  {
    "id": 121,
    "firstName": "Brigit",
    "lastName": "Maun",
    "email": "bmaun3c@opera.com",
    "dateOfBirth": "2020-09-14T11:33:32Z",
    "age": 29,
    "country": "Thailand",
    "phone": "9213749103"
  },
  {
    "id": 122,
    "firstName": "Janis",
    "lastName": "Payze",
    "email": "jpayze3d@dailymail.co.uk",
    "dateOfBirth": "2019-04-09T02:50:05Z",
    "age": 46,
    "country": "Argentina",
    "phone": "9283159577"
  },
  {
    "id": 123,
    "firstName": "Kerrin",
    "lastName": "Biggam",
    "email": "kbiggam3e@fotki.com",
    "dateOfBirth": "1987-03-18T21:59:56Z",
    "age": 40,
    "country": "Russia",
    "phone": "5963718207"
  },
  {
    "id": 124,
    "firstName": "Herrick",
    "lastName": "Miranda",
    "email": "hmiranda3f@hostgator.com",
    "dateOfBirth": "2013-06-12T16:07:07Z",
    "age": 54,
    "country": "Sweden",
    "phone": "1589750048"
  },
  {
    "id": 125,
    "firstName": "Vanya",
    "lastName": "Aris",
    "email": "varis3g@ovh.net",
    "dateOfBirth": "1973-03-10T18:53:47Z",
    "age": 20,
    "country": "Portugal",
    "phone": "7612184227"
  },
  {
    "id": 126,
    "firstName": "Orlando",
    "lastName": "Widmoor",
    "email": "owidmoor3h@free.fr",
    "dateOfBirth": "1997-03-07T16:20:06Z",
    "age": 41,
    "country": "China",
    "phone": "8889320498"
  },
  {
    "id": 127,
    "firstName": "Jorrie",
    "lastName": "Magson",
    "email": "jmagson3i@moonfruit.com",
    "dateOfBirth": "2008-10-25T22:38:17Z",
    "age": 55,
    "country": "Brazil",
    "phone": "3171545938"
  },
  {
    "id": 128,
    "firstName": "Madelaine",
    "lastName": "Iamittii",
    "email": "miamittii3j@blogs.com",
    "dateOfBirth": "2017-03-26T14:55:12Z",
    "age": 39,
    "country": "China",
    "phone": "4655330707"
  },
  {
    "id": 129,
    "firstName": "Margareta",
    "lastName": "Kloster",
    "email": "mkloster3k@phpbb.com",
    "dateOfBirth": "1993-09-25T05:15:43Z",
    "age": 40,
    "country": "Colombia",
    "phone": "2185182141"
  },
  {
    "id": 130,
    "firstName": "Hali",
    "lastName": "Lanfranconi",
    "email": "hlanfranconi3l@dailymotion.com",
    "dateOfBirth": "1972-08-26T19:51:00Z",
    "age": 19,
    "country": "China",
    "phone": "8927325743"
  },
  {
    "id": 131,
    "firstName": "Denver",
    "lastName": "Volante",
    "email": "dvolante3m@smugmug.com",
    "dateOfBirth": "1999-09-02T21:47:10Z",
    "age": 23,
    "country": "Colombia",
    "phone": "9409218270"
  },
  {
    "id": 132,
    "firstName": "Eydie",
    "lastName": "Willshere",
    "email": "ewillshere3n@uiuc.edu",
    "dateOfBirth": "1982-08-20T07:33:04Z",
    "age": 34,
    "country": "China",
    "phone": "5725605932"
  },
  {
    "id": 133,
    "firstName": "Napoleon",
    "lastName": "Streatfeild",
    "email": "nstreatfeild3o@latimes.com",
    "dateOfBirth": "1977-08-06T15:54:17Z",
    "age": 36,
    "country": "Nigeria",
    "phone": "2282453361"
  },
  {
    "id": 134,
    "firstName": "Rubia",
    "lastName": "Bevington",
    "email": "rbevington3p@zdnet.com",
    "dateOfBirth": "1982-03-01T21:15:36Z",
    "age": 24,
    "country": "Poland",
    "phone": "1322897920"
  },
  {
    "id": 135,
    "firstName": "Garland",
    "lastName": "Meddick",
    "email": "gmeddick3q@yellowbook.com",
    "dateOfBirth": "2013-07-17T22:30:09Z",
    "age": 58,
    "country": "Ireland",
    "phone": "6354225096"
  },
  {
    "id": 136,
    "firstName": "Lulu",
    "lastName": "Georgot",
    "email": "lgeorgot3r@home.pl",
    "dateOfBirth": "1981-01-17T14:15:01Z",
    "age": 50,
    "country": "Indonesia",
    "phone": "5948217286"
  },
  {
    "id": 137,
    "firstName": "Lisabeth",
    "lastName": "Soldi",
    "email": "lsoldi3s@tumblr.com",
    "dateOfBirth": "2001-02-14T15:49:36Z",
    "age": 46,
    "country": "Indonesia",
    "phone": "5091605825"
  },
  {
    "id": 138,
    "firstName": "Bird",
    "lastName": "Wastell",
    "email": "bwastell3t@unc.edu",
    "dateOfBirth": "1978-12-31T23:37:37Z",
    "age": 38,
    "country": "Democratic Republic of the Congo",
    "phone": "2129929714"
  },
  {
    "id": 139,
    "firstName": "Jaclyn",
    "lastName": "Morrilly",
    "email": "jmorrilly3u@va.gov",
    "dateOfBirth": "1998-03-05T23:54:59Z",
    "age": 32,
    "country": "Czech Republic",
    "phone": "6779755968"
  },
  {
    "id": 140,
    "firstName": "Betteanne",
    "lastName": "Almon",
    "email": "balmon3v@epa.gov",
    "dateOfBirth": "1994-12-03T13:08:52Z",
    "age": 43,
    "country": "China",
    "phone": "4636902854"
  },
  {
    "id": 141,
    "firstName": "Shaughn",
    "lastName": "Partrick",
    "email": "spartrick3w@va.gov",
    "dateOfBirth": "1999-10-16T03:55:02Z",
    "age": 58,
    "country": "Philippines",
    "phone": "9495810540"
  },
  {
    "id": 142,
    "firstName": "Claudio",
    "lastName": "Gahagan",
    "email": "cgahagan3x@apple.com",
    "dateOfBirth": "1985-03-13T16:52:15Z",
    "age": 38,
    "country": "Cameroon",
    "phone": "3989765002"
  },
  {
    "id": 143,
    "firstName": "Aggi",
    "lastName": "Flindall",
    "email": "aflindall3y@wix.com",
    "dateOfBirth": "1990-04-28T17:41:16Z",
    "age": 27,
    "country": "United States",
    "phone": "7028302030"
  },
  {
    "id": 144,
    "firstName": "Rufus",
    "lastName": "Pahler",
    "email": "rpahler3z@mayoclinic.com",
    "dateOfBirth": "1991-11-02T10:15:51Z",
    "age": 50,
    "country": "China",
    "phone": "2941648302"
  },
  {
    "id": 145,
    "firstName": "Maurise",
    "lastName": "Tibbs",
    "email": "mtibbs40@latimes.com",
    "dateOfBirth": "1993-06-06T04:41:20Z",
    "age": 54,
    "country": "United States",
    "phone": "9545272495"
  },
  {
    "id": 146,
    "firstName": "Tedie",
    "lastName": "McTavish",
    "email": "tmctavish41@prlog.org",
    "dateOfBirth": "2019-03-01T18:24:34Z",
    "age": 36,
    "country": "Russia",
    "phone": "9975470221"
  },
  {
    "id": 147,
    "firstName": "Deena",
    "lastName": "Hearnes",
    "email": "dhearnes42@google.com.hk",
    "dateOfBirth": "2007-04-28T04:00:21Z",
    "age": 36,
    "country": "Indonesia",
    "phone": "9599119958"
  },
  {
    "id": 148,
    "firstName": "Harri",
    "lastName": "Glencross",
    "email": "hglencross43@ameblo.jp",
    "dateOfBirth": "1986-01-06T23:16:54Z",
    "age": 55,
    "country": "Portugal",
    "phone": "5606621344"
  },
  {
    "id": 149,
    "firstName": "Kacey",
    "lastName": "Gillespie",
    "email": "kgillespie44@pcworld.com",
    "dateOfBirth": "2006-09-11T07:59:32Z",
    "age": 38,
    "country": "Portugal",
    "phone": "4353315855"
  },
  {
    "id": 150,
    "firstName": "Kelvin",
    "lastName": "Mixhel",
    "email": "kmixhel45@wikispaces.com",
    "dateOfBirth": "1971-06-07T02:47:59Z",
    "age": 21,
    "country": "China",
    "phone": "8128454516"
  },
  {
    "id": 151,
    "firstName": "Tynan",
    "lastName": "Gatling",
    "email": "tgatling46@macromedia.com",
    "dateOfBirth": "1992-03-10T16:00:49Z",
    "age": 43,
    "country": "United States",
    "phone": "8591240265"
  },
  {
    "id": 152,
    "firstName": "Emlyn",
    "lastName": "Waight",
    "email": "ewaight47@qq.com",
    "dateOfBirth": "1979-02-16T22:34:52Z",
    "age": 35,
    "country": "China",
    "phone": "1896407153"
  },
  {
    "id": 153,
    "firstName": "Katha",
    "lastName": "Woloschinski",
    "email": "kwoloschinski48@cdc.gov",
    "dateOfBirth": "2008-04-04T12:23:44Z",
    "age": 42,
    "country": "Luxembourg",
    "phone": "5667808167"
  },
  {
    "id": 154,
    "firstName": "Timothea",
    "lastName": "Adnet",
    "email": "tadnet49@fotki.com",
    "dateOfBirth": "2019-09-05T01:20:28Z",
    "age": 21,
    "country": "Thailand",
    "phone": "3749301332"
  },
  {
    "id": 155,
    "firstName": "Casi",
    "lastName": "L'Archer",
    "email": "clarcher4a@phoca.cz",
    "dateOfBirth": "1977-05-26T01:36:44Z",
    "age": 19,
    "country": "Sudan",
    "phone": "6948246487"
  },
  {
    "id": 156,
    "firstName": "Katrina",
    "lastName": "Dannel",
    "email": "kdannel4b@zdnet.com",
    "dateOfBirth": "1999-05-01T10:29:51Z",
    "age": 50,
    "country": "Russia",
    "phone": "8584778274"
  },
  {
    "id": 157,
    "firstName": "Carlo",
    "lastName": "Jenno",
    "email": "cjenno4c@yellowpages.com",
    "dateOfBirth": "1989-06-04T20:23:25Z",
    "age": 41,
    "country": "China",
    "phone": "2819476413"
  },
  {
    "id": 158,
    "firstName": "Tanya",
    "lastName": "Hillum",
    "email": "thillum4d@indiatimes.com",
    "dateOfBirth": "1988-11-01T12:34:18Z",
    "age": 53,
    "country": "Indonesia",
    "phone": "3253598199"
  },
  {
    "id": 159,
    "firstName": "Hamilton",
    "lastName": "Wellington",
    "email": "hwellington4e@topsy.com",
    "dateOfBirth": "1993-08-07T13:41:41Z",
    "age": 49,
    "country": "Tanzania",
    "phone": "9938683742"
  },
  {
    "id": 160,
    "firstName": "Judon",
    "lastName": "Fozzard",
    "email": "jfozzard4f@nasa.gov",
    "dateOfBirth": "2014-09-16T18:25:04Z",
    "age": 48,
    "country": "Venezuela",
    "phone": "3968022740"
  },
  {
    "id": 161,
    "firstName": "Drucy",
    "lastName": "Harvison",
    "email": "dharvison4g@prnewswire.com",
    "dateOfBirth": "2012-02-21T01:14:25Z",
    "age": 21,
    "country": "Brazil",
    "phone": "4698193176"
  },
  {
    "id": 162,
    "firstName": "Mattie",
    "lastName": "Minerdo",
    "email": "mminerdo4h@army.mil",
    "dateOfBirth": "2002-07-31T17:38:58Z",
    "age": 38,
    "country": "Indonesia",
    "phone": "4802662353"
  },
  {
    "id": 163,
    "firstName": "Reidar",
    "lastName": "Freshwater",
    "email": "rfreshwater4i@printfriendly.com",
    "dateOfBirth": "2010-02-10T19:24:04Z",
    "age": 31,
    "country": "China",
    "phone": "8156406628"
  },
  {
    "id": 164,
    "firstName": "Perle",
    "lastName": "Sheirlaw",
    "email": "psheirlaw4j@eventbrite.com",
    "dateOfBirth": "2009-11-29T10:06:04Z",
    "age": 49,
    "country": "China",
    "phone": "7878012246"
  },
  {
    "id": 165,
    "firstName": "Mady",
    "lastName": "Lewcock",
    "email": "mlewcock4k@usa.gov",
    "dateOfBirth": "1987-03-18T17:11:45Z",
    "age": 53,
    "country": "Yemen",
    "phone": "4614362406"
  },
  {
    "id": 166,
    "firstName": "Dallas",
    "lastName": "Crowne",
    "email": "dcrowne4l@taobao.com",
    "dateOfBirth": "1994-06-14T07:25:33Z",
    "age": 45,
    "country": "Russia",
    "phone": "8356308242"
  },
  {
    "id": 167,
    "firstName": "Fredericka",
    "lastName": "Jullian",
    "email": "fjullian4m@google.pl",
    "dateOfBirth": "1987-04-07T06:00:10Z",
    "age": 28,
    "country": "Venezuela",
    "phone": "9048737653"
  },
  {
    "id": 168,
    "firstName": "Kory",
    "lastName": "Paladini",
    "email": "kpaladini4n@wikipedia.org",
    "dateOfBirth": "2015-10-03T18:22:58Z",
    "age": 28,
    "country": "Chile",
    "phone": "7593536528"
  },
  {
    "id": 169,
    "firstName": "Rafaello",
    "lastName": "Sambidge",
    "email": "rsambidge4o@accuweather.com",
    "dateOfBirth": "2016-09-04T11:07:27Z",
    "age": 52,
    "country": "Thailand",
    "phone": "8731271461"
  },
  {
    "id": 170,
    "firstName": "Dav",
    "lastName": "Seale",
    "email": "dseale4p@vimeo.com",
    "dateOfBirth": "1973-07-21T07:44:22Z",
    "age": 29,
    "country": "Philippines",
    "phone": "4666679196"
  },
  {
    "id": 171,
    "firstName": "Lisa",
    "lastName": "Askaw",
    "email": "laskaw4q@wiley.com",
    "dateOfBirth": "1973-08-22T08:39:18Z",
    "age": 53,
    "country": "China",
    "phone": "2247775769"
  },
  {
    "id": 172,
    "firstName": "Tris",
    "lastName": "Krelle",
    "email": "tkrelle4r@howstuffworks.com",
    "dateOfBirth": "1995-01-22T15:04:13Z",
    "age": 56,
    "country": "Syria",
    "phone": "4916363765"
  },
  {
    "id": 173,
    "firstName": "Derwin",
    "lastName": "Kettley",
    "email": "dkettley4s@github.com",
    "dateOfBirth": "1975-04-06T23:34:27Z",
    "age": 33,
    "country": "Vanuatu",
    "phone": "6859979615"
  },
  {
    "id": 174,
    "firstName": "Marya",
    "lastName": "Caselli",
    "email": "mcaselli4t@geocities.jp",
    "dateOfBirth": "1992-06-11T18:53:22Z",
    "age": 21,
    "country": "Peru",
    "phone": "4979585110"
  },
  {
    "id": 175,
    "firstName": "Tremain",
    "lastName": "Slopier",
    "email": "tslopier4u@themeforest.net",
    "dateOfBirth": "2016-04-20T22:37:16Z",
    "age": 21,
    "country": "Russia",
    "phone": "9407811628"
  },
  {
    "id": 176,
    "firstName": "Berkeley",
    "lastName": "Jacmar",
    "email": "bjacmar4v@seattletimes.com",
    "dateOfBirth": "2013-02-25T21:55:11Z",
    "age": 37,
    "country": "Colombia",
    "phone": "1687767375"
  },
  {
    "id": 177,
    "firstName": "Muire",
    "lastName": "Lahiff",
    "email": "mlahiff4w@google.nl",
    "dateOfBirth": "1978-11-26T12:43:55Z",
    "age": 37,
    "country": "Burkina Faso",
    "phone": "2519588720"
  },
  {
    "id": 178,
    "firstName": "Peder",
    "lastName": "Rousell",
    "email": "prousell4x@macromedia.com",
    "dateOfBirth": "1975-02-28T05:36:32Z",
    "age": 41,
    "country": "South Africa",
    "phone": "3707076197"
  },
  {
    "id": 179,
    "firstName": "Romain",
    "lastName": "Shreeve",
    "email": "rshreeve4y@mlb.com",
    "dateOfBirth": "2010-10-02T23:21:46Z",
    "age": 36,
    "country": "Peru",
    "phone": "8556977748"
  },
  {
    "id": 180,
    "firstName": "Leonard",
    "lastName": "Pesticcio",
    "email": "lpesticcio4z@twitpic.com",
    "dateOfBirth": "1987-07-02T11:30:40Z",
    "age": 47,
    "country": "Nigeria",
    "phone": "5513340866"
  },
  {
    "id": 181,
    "firstName": "Tanny",
    "lastName": "Walklate",
    "email": "twalklate50@exblog.jp",
    "dateOfBirth": "2004-01-15T01:12:41Z",
    "age": 56,
    "country": "China",
    "phone": "1098865368"
  },
  {
    "id": 182,
    "firstName": "Elsi",
    "lastName": "Faherty",
    "email": "efaherty51@nifty.com",
    "dateOfBirth": "2003-07-04T13:02:56Z",
    "age": 36,
    "country": "France",
    "phone": "4073920533"
  },
  {
    "id": 183,
    "firstName": "Aurea",
    "lastName": "Shaudfurth",
    "email": "ashaudfurth52@odnoklassniki.ru",
    "dateOfBirth": "2012-07-16T05:45:53Z",
    "age": 33,
    "country": "Poland",
    "phone": "9732253244"
  },
  {
    "id": 184,
    "firstName": "Fidelity",
    "lastName": "Kingswood",
    "email": "fkingswood53@dagondesign.com",
    "dateOfBirth": "2010-03-22T16:53:56Z",
    "age": 28,
    "country": "Poland",
    "phone": "3825023023"
  },
  {
    "id": 185,
    "firstName": "Trudie",
    "lastName": "Booth",
    "email": "tbooth54@edublogs.org",
    "dateOfBirth": "1981-08-07T00:22:15Z",
    "age": 32,
    "country": "Indonesia",
    "phone": "8727510886"
  },
  {
    "id": 186,
    "firstName": "Tyler",
    "lastName": "Canape",
    "email": "tcanape55@squidoo.com",
    "dateOfBirth": "1971-04-19T18:59:01Z",
    "age": 25,
    "country": "France",
    "phone": "7071161886"
  },
  {
    "id": 187,
    "firstName": "Merwyn",
    "lastName": "Noel",
    "email": "mnoel56@list-manage.com",
    "dateOfBirth": "2013-10-07T08:46:54Z",
    "age": 25,
    "country": "Palestinian Territory",
    "phone": "2685172119"
  },
  {
    "id": 188,
    "firstName": "Aurelia",
    "lastName": "Meekin",
    "email": "ameekin57@lycos.com",
    "dateOfBirth": "1997-04-13T06:00:49Z",
    "age": 43,
    "country": "Nigeria",
    "phone": "4087105585"
  },
  {
    "id": 189,
    "firstName": "Erminie",
    "lastName": "Le Barre",
    "email": "elebarre58@ebay.com",
    "dateOfBirth": "1983-04-19T02:33:05Z",
    "age": 32,
    "country": "Japan",
    "phone": "5198076119"
  },
  {
    "id": 190,
    "firstName": "Jen",
    "lastName": "Joerning",
    "email": "jjoerning59@va.gov",
    "dateOfBirth": "2002-05-10T15:37:41Z",
    "age": 42,
    "country": "Sweden",
    "phone": "7192198973"
  },
  {
    "id": 191,
    "firstName": "Art",
    "lastName": "Matthis",
    "email": "amatthis5a@delicious.com",
    "dateOfBirth": "1971-03-10T03:03:19Z",
    "age": 49,
    "country": "Nigeria",
    "phone": "8867269709"
  },
  {
    "id": 192,
    "firstName": "Stefanie",
    "lastName": "Tayspell",
    "email": "stayspell5b@cdc.gov",
    "dateOfBirth": "1981-05-15T04:50:51Z",
    "age": 44,
    "country": "Indonesia",
    "phone": "8682783429"
  },
  {
    "id": 193,
    "firstName": "Debora",
    "lastName": "Acott",
    "email": "dacott5c@dropbox.com",
    "dateOfBirth": "2018-05-18T09:01:57Z",
    "age": 32,
    "country": "Argentina",
    "phone": "5981706890"
  },
  {
    "id": 194,
    "firstName": "Griffith",
    "lastName": "McCard",
    "email": "gmccard5d@discovery.com",
    "dateOfBirth": "2005-01-08T18:57:29Z",
    "age": 46,
    "country": "Brazil",
    "phone": "9166266711"
  },
  {
    "id": 195,
    "firstName": "Zechariah",
    "lastName": "Maciocia",
    "email": "zmaciocia5e@ehow.com",
    "dateOfBirth": "1993-08-18T03:41:30Z",
    "age": 45,
    "country": "Indonesia",
    "phone": "9493745606"
  },
  {
    "id": 196,
    "firstName": "Levi",
    "lastName": "Bleacher",
    "email": "lbleacher5f@howstuffworks.com",
    "dateOfBirth": "1975-05-17T23:21:10Z",
    "age": 47,
    "country": "Japan",
    "phone": "8837663917"
  },
  {
    "id": 197,
    "firstName": "Dylan",
    "lastName": "Llewelly",
    "email": "dllewelly5g@blogspot.com",
    "dateOfBirth": "1978-09-17T18:09:24Z",
    "age": 25,
    "country": "Indonesia",
    "phone": "2354116170"
  },
  {
    "id": 198,
    "firstName": "Lewes",
    "lastName": "Rootes",
    "email": "lrootes5h@narod.ru",
    "dateOfBirth": "2002-12-21T19:20:02Z",
    "age": 43,
    "country": "Serbia",
    "phone": "7268678307"
  },
  {
    "id": 199,
    "firstName": "Mark",
    "lastName": "Dugald",
    "email": "ldugald5i@bizjournals.com",
    "dateOfBirth": "1983-05-23T04:14:12Z",
    "age": 28,
    "country": "Philippines",
    "phone": "7279447449"
  },
  {
    "id": 200,
    "firstName": "Derwin",
    "lastName": "Burroughes",
    "email": "dburroughes5j@hp.com",
    "dateOfBirth": "1983-03-02T09:58:54Z",
    "age": 27,
    "country": "Azerbaijan",
    "phone": "6728688611"
  }
]
